{
    "__type": "Trial",
    "index": 9,
    "trial_type": null,
    "ttl_seconds": null,
    "status": {
        "__type": "TrialStatus",
        "name": "CANDIDATE"
    },
    "time_created": {
        "__type": "datetime",
        "value": "2023-09-05 10:10:21.249049"
    },
    "time_completed": null,
    "time_staged": null,
    "time_run_started": null,
    "abandoned_reason": null,
    "run_metadata": {},
    "stop_metadata": {},
    "generator_run": {
        "__type": "GeneratorRun",
        "arms": [
            {
                "__type": "Arm",
                "parameters": {
                    "x0": 0.6577184610068798,
                    "x1": 0.9337133802473545,
                    "x2": 0.9577757762745023,
                    "x3": 0.16036025527864695,
                    "x4": 0.7716413559392095,
                    "x5": 0.9886263897642493
                },
                "name": "9_0"
            }
        ],
        "weights": [
            1.0
        ],
        "optimization_config": null,
        "search_space": null,
        "time_created": {
            "__type": "datetime",
            "value": "2023-09-05 10:10:21.248970"
        },
        "model_predictions": null,
        "best_arm_predictions": null,
        "generator_run_type": null,
        "index": 0,
        "fit_time": 0.002199249982368201,
        "gen_time": 0.0022917079913895577,
        "model_key": "Sobol",
        "model_kwargs": {
            "seed": null,
            "deduplicate": true,
            "init_position": 9,
            "scramble": true,
            "generated_points": {
                "__type": "ndarray",
                "value": [
                    [
                        0.044871218502521515,
                        0.3218871057033539,
                        0.607721209526062,
                        0.010939295403659344,
                        0.9225975275039673,
                        0.09617611765861511
                    ],
                    [
                        0.73201266489923,
                        0.3137906324118376,
                        0.49483539164066315,
                        0.8232826832681894,
                        0.7677581962198019,
                        0.6537844622507691
                    ],
                    [
                        0.7182020843029022,
                        0.24275563284754753,
                        0.32506132032722235,
                        0.9885101979598403,
                        0.406885189935565,
                        0.8243899559602141
                    ],
                    [
                        0.38822016492486,
                        0.5634880857542157,
                        0.06349657569080591,
                        0.586815582588315,
                        0.1930325422435999,
                        0.4764972757548094
                    ],
                    [
                        0.6569762509316206,
                        0.29673738684505224,
                        0.13369906693696976,
                        0.2163340412080288,
                        0.3231657175347209,
                        0.5083151180297136
                    ],
                    [
                        0.3239260111004114,
                        0.9805985279381275,
                        0.1514215860515833,
                        0.9384361999109387,
                        0.3036146014928818,
                        0.5394862797111273
                    ],
                    [
                        0.9340457022190094,
                        0.26264371257275343,
                        0.30353494081646204,
                        0.2979101138189435,
                        0.790505139157176,
                        0.7738114818930626
                    ],
                    [
                        0.22345104720443487,
                        0.6423176666721702,
                        0.8144994741305709,
                        0.05149886850267649,
                        0.9741508578881621,
                        0.5215477533638477
                    ],
                    [
                        0.9012106908485293,
                        0.024473613128066063,
                        0.8279877239838243,
                        0.02931827772408724,
                        0.19692742452025414,
                        0.13250281382352114
                    ]
                ]
            },
            "fallback_to_sample_polytope": false
        },
        "bridge_kwargs": {
            "transforms": [
                {
                    "__type": "Type[Transform]",
                    "index_in_registry": 9,
                    "transform_type": "<class 'ax.modelbridge.transforms.remove_fixed.RemoveFixed'>"
                },
                {
                    "__type": "Type[Transform]",
                    "index_in_registry": 7,
                    "transform_type": "<class 'ax.modelbridge.transforms.choice_encode.OrderedChoiceEncode'>"
                },
                {
                    "__type": "Type[Transform]",
                    "index_in_registry": 6,
                    "transform_type": "<class 'ax.modelbridge.transforms.one_hot.OneHot'>"
                },
                {
                    "__type": "Type[Transform]",
                    "index_in_registry": 3,
                    "transform_type": "<class 'ax.modelbridge.transforms.int_to_float.IntToFloat'>"
                },
                {
                    "__type": "Type[Transform]",
                    "index_in_registry": 5,
                    "transform_type": "<class 'ax.modelbridge.transforms.log.Log'>"
                },
                {
                    "__type": "Type[Transform]",
                    "index_in_registry": 20,
                    "transform_type": "<class 'ax.modelbridge.transforms.logit.Logit'>"
                },
                {
                    "__type": "Type[Transform]",
                    "index_in_registry": 15,
                    "transform_type": "<class 'ax.modelbridge.transforms.unit_x.UnitX'>"
                }
            ],
            "transform_configs": null,
            "status_quo_name": null,
            "status_quo_features": null,
            "optimization_config": null,
            "fit_out_of_design": false,
            "fit_abandoned": false,
            "fit_tracking_metrics": true,
            "fit_on_init": true
        },
        "gen_metadata": {},
        "model_state_after_gen": {
            "generated_points": {
                "__type": "ndarray",
                "value": [
                    [
                        0.044871218502521515,
                        0.3218871057033539,
                        0.607721209526062,
                        0.010939295403659344,
                        0.9225975275039673,
                        0.09617611765861511
                    ],
                    [
                        0.73201266489923,
                        0.3137906324118376,
                        0.49483539164066315,
                        0.8232826832681894,
                        0.7677581962198019,
                        0.6537844622507691
                    ],
                    [
                        0.7182020843029022,
                        0.24275563284754753,
                        0.32506132032722235,
                        0.9885101979598403,
                        0.406885189935565,
                        0.8243899559602141
                    ],
                    [
                        0.38822016492486,
                        0.5634880857542157,
                        0.06349657569080591,
                        0.586815582588315,
                        0.1930325422435999,
                        0.4764972757548094
                    ],
                    [
                        0.6569762509316206,
                        0.29673738684505224,
                        0.13369906693696976,
                        0.2163340412080288,
                        0.3231657175347209,
                        0.5083151180297136
                    ],
                    [
                        0.3239260111004114,
                        0.9805985279381275,
                        0.1514215860515833,
                        0.9384361999109387,
                        0.3036146014928818,
                        0.5394862797111273
                    ],
                    [
                        0.9340457022190094,
                        0.26264371257275343,
                        0.30353494081646204,
                        0.2979101138189435,
                        0.790505139157176,
                        0.7738114818930626
                    ],
                    [
                        0.22345104720443487,
                        0.6423176666721702,
                        0.8144994741305709,
                        0.05149886850267649,
                        0.9741508578881621,
                        0.5215477533638477
                    ],
                    [
                        0.9012106908485293,
                        0.024473613128066063,
                        0.8279877239838243,
                        0.02931827772408724,
                        0.19692742452025414,
                        0.13250281382352114
                    ],
                    [
                        0.6577184610068798,
                        0.9337133802473545,
                        0.9577757762745023,
                        0.16036025527864695,
                        0.7716413559392095,
                        0.9886263897642493
                    ]
                ]
            },
            "init_position": 10
        },
        "generation_step_index": 0,
        "candidate_metadata_by_arm_signature": null
    },
    "runner": null,
    "num_arms_created": 1,
    "generation_step_index": 0,
    "properties": {}
}